cvxpy_translation/__init__.py
cvxpy_translation/_version.py
cvxpy_translation/exceptions.py
cvxpy_translation/interface.py
cvxpy_translation/py.typed
cvxpy_translation/utils.py
cvxpy_translation/gurobi/__init__.py
cvxpy_translation/gurobi/interface.py
cvxpy_translation/gurobi/translation.py
cvxpy_translation/scip/__init__.py
cvxpy_translation/scip/interface.py
cvxpy_translation/scip/translation.py
cvxpy_translation-2.0.1.dist-info/METADATA
cvxpy_translation-2.0.1.dist-info/WHEEL
cvxpy_translation-2.0.1.dist-info/licenses/LICENSE
cvxpy_translation-2.0.1.dist-info/RECORD
