Metadata-Version: 2.4
Name: cvxpy-translation
Version: 2.0.1
Summary: Translate CVXPY problems into solvers' native models
Project-URL: Documentation, https://github.com/jonathanberthias/cvxpy-translation#readme
Project-URL: Issues, https://github.com/jonathanberthias/cvxpy-translation/issues
Project-URL: Source, https://github.com/jonathanberthias/cvxpy-translation
Author-email: Jonathan Berthias <jvberthias@gmail.com>
License-Expression: Apache-2.0
License-File: LICENSE
Keywords: cvxpy,gurobi,gurobipy,optimization
Classifier: Development Status :: 4 - Beta
Classifier: Intended Audience :: Science/Research
Classifier: Programming Language :: Python
Classifier: Programming Language :: Python :: 3 :: Only
Classifier: Programming Language :: Python :: 3.9
Classifier: Programming Language :: Python :: 3.10
Classifier: Programming Language :: Python :: 3.11
Classifier: Programming Language :: Python :: 3.12
Classifier: Programming Language :: Python :: 3.13
Classifier: Programming Language :: Python :: Implementation :: CPython
Classifier: Topic :: Scientific/Engineering :: Mathematics
Requires-Python: >=3.9
Requires-Dist: numpy>=1.23.0
Requires-Dist: scipy>=1.5.4
Provides-Extra: cvxpy
Requires-Dist: cvxpy>=1.1.16; extra == 'cvxpy'
Provides-Extra: cvxpy-base
Requires-Dist: cvxpy-base>=1.1.16; extra == 'cvxpy-base'
Provides-Extra: gurobi
Requires-Dist: gurobipy; extra == 'gurobi'
Provides-Extra: scip
Requires-Dist: pyscipopt>=5.4.1; extra == 'scip'
